setup.py
cassandra/Cassandra.py
cassandra/__init__.py
cassandra/constants.py
cassandra/ttypes.py
python_cassandra.egg-info/PKG-INFO
python_cassandra.egg-info/SOURCES.txt
python_cassandra.egg-info/dependency_links.txt
python_cassandra.egg-info/requires.txt
python_cassandra.egg-info/top_level.txt
scripts/Cassandra-remote