Metadata-Version: 1.0
Name: python-cassandra
Version: 0.5.0
Summary: Thrift client for Cassandra
Home-page: http://incubator.apache.org/cassandra/
Author: Ian Eure
Author-email: ian.eure@gmail.com
License: UNKNOWN
Keywords: database cassandra
Platform: UNKNOWN
